enaml_native-4.5.4.dist-info/METADATA
enaml_native-4.5.4.dist-info/RECORD
enaml_native-4.5.4.dist-info/WHEEL
enaml_native-4.5.4.dist-info/top_level.txt
enamlnative/__init__.py
enamlnative/android/__init__.py
enamlnative/android/android_action_menu_view.py
enamlnative/android/android_activity.py
enamlnative/android/android_activity_indicator.py
enamlnative/android/android_adapter.py
enamlnative/android/android_app_bar_layout.py
enamlnative/android/android_auto_complete_text_view.py
enamlnative/android/android_bottom_sheet_dialog.py
enamlnative/android/android_button.py
enamlnative/android/android_calendar_view.py
enamlnative/android/android_camera.py
enamlnative/android/android_card_view.py
enamlnative/android/android_checkbox.py
enamlnative/android/android_chronometer.py
enamlnative/android/android_compound_button.py
enamlnative/android/android_content.py
enamlnative/android/android_coordinator_layout.py
enamlnative/android/android_date_picker.py
enamlnative/android/android_dialog.py
enamlnative/android/android_drawer_layout.py
enamlnative/android/android_edit_text.py
enamlnative/android/android_flexbox.py
enamlnative/android/android_fragment.py
enamlnative/android/android_frame_layout.py
enamlnative/android/android_grid_layout.py
enamlnative/android/android_iconify.py
enamlnative/android/android_image_view.py
enamlnative/android/android_linear_layout.py
enamlnative/android/android_list_view.py
enamlnative/android/android_location.py
enamlnative/android/android_notification.py
enamlnative/android/android_picker.py
enamlnative/android/android_popup_window.py
enamlnative/android/android_progress_bar.py
enamlnative/android/android_radio_button.py
enamlnative/android/android_radio_group.py
enamlnative/android/android_rating_bar.py
enamlnative/android/android_relative_layout.py
enamlnative/android/android_scroll_view.py
enamlnative/android/android_seek_bar.py
enamlnative/android/android_sensors.py
enamlnative/android/android_snackbar.py
enamlnative/android/android_spinner.py
enamlnative/android/android_surface_view.py
enamlnative/android/android_swipe_refresh_layout.py
