Metadata-Version: 2.1
Name: enaml-native
Version: 4.5.4
Summary: Build native mobile apps in python
Home-page: https://github.com/codelv/enaml-native/
Author: CodeLV
Author-email: frmdstryr@gmail.com
License: MIT
Platform: UNKNOWN
